meshnetworkx/__init__.py
meshnetworkx-0.1.2.dist-info/LICENSE
meshnetworkx-0.1.2.dist-info/METADATA
meshnetworkx-0.1.2.dist-info/WHEEL
meshnetworkx-0.1.2.dist-info/top_level.txt
meshnetworkx-0.1.2.dist-info/RECORD
