Metadata-Version: 2.1
Name: meshnetworkx
Version: 0.1.2
Summary: Sync and use a networkX graph between multiple hosts through the power of Zenoh storages.
Author-email: "W. Meijer" <houterm+meshnetworkx@gmail.com>
Project-URL: Source, https://github.com/h0uter/meshnetworkx
Project-URL: Issues, https://github.com/h0uter/meshnetworkx/issues
Project-URL: Documentation, https://h0uter.github.io/meshnetworkx/
Requires-Python: >=3.10
License-File: LICENSE
Requires-Dist: eclipse-zenoh >=1.0.0
Requires-Dist: matplotlib >=3.9.2
Requires-Dist: networkx >=3.4.1
Provides-Extra: docs
Requires-Dist: mkdocs-material >=9.5.33 ; extra == 'docs'
Requires-Dist: mkdocstrings-python >=1.10.9 ; extra == 'docs'
Provides-Extra: examples
Requires-Dist: humid >=0.3.1 ; extra == 'examples'
Requires-Dist: nicegui >=2.5.0 ; extra == 'examples'
Provides-Extra: test
Requires-Dist: pytest >=8.3.3 ; extra == 'test'
